{
  "patient_id": null,
  "report_date": null,
  "institution": null,
  "specimen_type": "Mastectomy",
  "laterality": "Left",
  "tumor_site": "breast, NOS C50.9",
  "histologic_type": "Invasive ductal carcinoma with extensive intraductal component",
  "DCIS_present": "yes",
  "DCIS_grade": "high",
  "LCIS_present": null,
  "necrosis": null,
  "lymphovascular_invasion": "Absent",
  "perineural_invasion": null,
  "tumor_size_cm": 3.7,
  "tumor_size_raw": "3.7 cm",
  "tumor_focality": null,
  "additional_tumor_foci_cm": "3.3 x 2.7 cm",
  "skin_involvement": null,
  "nipple_involvement": null,
  "chest_wall_involvement": null,
  "pectoralis_involvement": null,
  "inflammatory_carcinoma": null,
  "pathologic_T": "pT2",
  "lymph_nodes_examined": 7,
  "lymph_nodes_positive": 1,
  "axillary_ln_level": null,
  "axillary_ln_fixed_matted": null,
  "axillary_ln_micrometastasis": "yes",
  "internal_mammary_positive": null,
  "infraclavicular_positive": null,
  "supraclavicular_positive": null,
  "ln_extranodal_extension": null,
  "sentinel_node_biopsy_done": "yes",
  "pathologic_N": "pN1mi",
  "distant_metastasis": null,
  "metastasis_sites": null,
  "pathologic_M": "cM0",
  "nottingham_grade": 3,
  "tubule_formation_score": 3,
  "nuclear_pleomorphism_score": 3,
  "mitotic_count_score": 3,
  "mitotic_count_raw": "Greater than 10 mitoses per 10 HPF",
  "ER_status": "positive",
  "ER_percent": null,
  "ER_allred_score": null,
  "PR_status": "negative",
  "PR_percent": null,
  "PR_allred_score": null,
  "HER2_status": "negative",
  "HER2_IHC_score": null,
  "HER2_ISH_ratio": null,
  "HER2_method": "immunohistochemistry",
  "Ki67_percent": null,
  "margins": "Margins uninvolved by invasive carcinoma",
  "margin_distance_mm": null,
  "margin_location": "Deep margin focally positive for DCIS",
  "report_states_T": "pT2",
  "report_states_N": "pN1mi",
  "report_states_M": "pMX",
  "report_states_overall_stage": null,
  "derived_anatomic_stage": null,
  "derived_prognostic_stage": null,
  "missing_for_anatomic_stage": [],
  "missing_for_prognostic_stage": [],
  "extraction_confidence": "high",
  "_m_defaulted": true,
  "_folder_id": "21ab84a0-99b4-4313-870a-f59fe5719858",
  "_pdf_name": "TCGA-EW-A2FS.F273B11F-D3CE-4619-BEC2-15C110567503.PDF",
  "_pages": 3,
  "_ml_class": "Stage_IIB",
  "_ml_label": 2
}